odoo/addons/stock_warehouse_calendar/README.rst
odoo/addons/stock_warehouse_calendar/__init__.py
odoo/addons/stock_warehouse_calendar/__manifest__.py
odoo/addons/stock_warehouse_calendar/i18n/ca.po
odoo/addons/stock_warehouse_calendar/i18n/es.po
odoo/addons/stock_warehouse_calendar/i18n/it.po
odoo/addons/stock_warehouse_calendar/i18n/stock_warehouse_calendar.pot
odoo/addons/stock_warehouse_calendar/i18n/zh_CN.po
odoo/addons/stock_warehouse_calendar/models/__init__.py
odoo/addons/stock_warehouse_calendar/models/stock_rule.py
odoo/addons/stock_warehouse_calendar/models/stock_warehouse.py
odoo/addons/stock_warehouse_calendar/readme/CONFIGURE.md
odoo/addons/stock_warehouse_calendar/readme/CONTRIBUTORS.md
odoo/addons/stock_warehouse_calendar/readme/DESCRIPTION.md
odoo/addons/stock_warehouse_calendar/readme/USAGE.md
odoo/addons/stock_warehouse_calendar/static/description/delay.gif
odoo/addons/stock_warehouse_calendar/static/description/icon.png
odoo/addons/stock_warehouse_calendar/static/description/index.html
odoo/addons/stock_warehouse_calendar/static/description/multi_step.gif
odoo/addons/stock_warehouse_calendar/static/description/warehouse_management.gif
odoo/addons/stock_warehouse_calendar/static/description/working_schedules.gif
odoo/addons/stock_warehouse_calendar/tests/__init__.py
odoo/addons/stock_warehouse_calendar/tests/test_stock_warehouse_calendar.py
odoo/addons/stock_warehouse_calendar/views/stock_warehouse_views.xml
odoo_addon_stock_warehouse_calendar-18.0.1.1.0.dist-info/METADATA
odoo_addon_stock_warehouse_calendar-18.0.1.1.0.dist-info/WHEEL
odoo_addon_stock_warehouse_calendar-18.0.1.1.0.dist-info/top_level.txt
odoo_addon_stock_warehouse_calendar-18.0.1.1.0.dist-info/RECORD
